django_qiniu_storage-2.3.0.dist-info/DESCRIPTION.rst
django_qiniu_storage-2.3.0.dist-info/WHEEL
django_qiniu_storage-2.3.0.dist-info/METADATA
django_qiniu_storage-2.3.0.dist-info/RECORD
django_qiniu_storage-2.3.0.dist-info/top_level.txt
django_qiniu_storage-2.3.0.dist-info/metadata.json
qiniustorage/utils.py
qiniustorage/backends.py
qiniustorage/__init__.py
