Metadata-Version: 2.0
Name: django-qiniu-storage
Version: 2.3.0
Summary: Django storage for Qiniu Cloud Storage
Home-page: https://github.com/glasslion/django-qiniu-storage
Author: Lijian Zhou
Author-email: glasslion@gmail.com
License: MIT
Keywords: qiniu django
Platform: UNKNOWN
Classifier: Development Status :: 3 - Alpha
Classifier: Intended Audience :: Developers
Classifier: Framework :: Django
Classifier: Environment :: Plugins
Classifier: License :: OSI Approved :: MIT License
Classifier: Programming Language :: Python :: 2
Classifier: Programming Language :: Python :: 2.6
Classifier: Programming Language :: Python :: 2.7
Requires-Dist: qiniu (>=7.0.1)
Requires-Dist: six
Requires-Dist: requests
